{"count":29,"data":{"2d863444-87aa-46d4-a9c1-0aaafbab1c90":{"brand":"Aeotec","model":"Smart Home Hub","generation":3,"revision":"N/A","category":"hub","type":"open","network":{"zigbee":["gen3"],"zWave":["plus"],"lan":["wifi"],"wifi":["2.4GHz","5GHz","ac"]},"control":["alexa","googleAssistant","smartThings"],"powerSource":["wall"],"amazonDP":{"eu":"B08NDH9NXN","com":"B08TWDNQ5Q"},"expandable":false,"productId":"2d863444-87aa-46d4-a9c1-0aaafbab1c90"},"9ee4cade-fccd-4d2a-bc23-6e41d1eb21b9":{"brand":"Aeotec","model":"MultiSensor 6","generation":6,"revision":"N/A","category":"sensor","senses":["humidity","light","motion","uv","temperature","vibration"],"network":{"zWave":["plus","gen5"]},"control":["smartThings"],"powerSource":["wall","battery"],"amazonDP":{"eu":"B0141FQDJQ","com":"B0151Z8ZQY"},"productId":"9ee4cade-fccd-4d2a-bc23-6e41d1eb21b9"},"c846940e-f68c-4b14-808b-5c35dee691de":{"brand":"Aeotec","model":"MultiSensor 7","generation":7,"revision":"N/A","category":"sensor","senses":["humidity","light","motion","uv","temperature","vibration"],"network":{"zWave":["plus","S2","gen7"]},"control":["smartThings"],"powerSource":["wall","battery"],"amazonDP":{"com":"B08XHZP7NV"},"productId":"c846940e-f68c-4b14-808b-5c35dee691de"},"239f42e6-0fa0-474f-b3bc-f1587445e35c":{"brand":"Amazon","model":"Echo","generation":4,"revision":"2020","category":"hub","type":"proprietary","network":{"zigbee":["gen3"],"lan":["wifi"],"wifi":["2.4GHz","5GHz","AC"],"bluetooth":[]},"control":["alexa"],"powerSource":["wall"],"amazonDP":{"eu":"B085FXHR38","pl":"B085H3DKLT","com":"B07XKF5RM3"},"expandable":false,"productId":"239f42e6-0fa0-474f-b3bc-f1587445e35c"},"d20c39d8-d1f5-4947-8cd3-b14632cb043a":{"brand":"Amazon","model":"Echo Dot with Clock","generation":4,"revision":"2020","category":"hub","type":"proprietary","network":{"lan":["wifi"],"wifi":["2.4GHz","5GHz","AC"],"bluetooth":[]},"control":["alexa"],"powerSource":["wall"],"amazonDP":{"eu":"B084J4KZ8J","com":"B07XJ8C8F7"},"expandable":false,"productId":"d20c39d8-d1f5-4947-8cd3-b14632cb043a"},"eb9c18d9-ba0c-4067-9c68-75b89d5d7392":{"brand":"Amazon","model":"Echo Dot","generation":4,"revision":"2020","category":"hub","type":"proprietary","network":{"lan":["wifi"],"wifi":["2.4GHz","5GHz","AC"],"bluetooth":[]},"control":["alexa"],"powerSource":["wall"],"amazonDP":{"eu":"B084DWG2VQ","pl":"B085K45C3","com":"B07XJ8C8F5"},"expandable":false,"productId":"eb9c18d9-ba0c-4067-9c68-75b89d5d7392"},"e5feff15-c052-4697-b4e4-86fdff437315":{"brand":"Apple","model":"HomePod mini","generation":"N/A","revision":"2020","category":"hub","type":"proprietary","network":{"thread":["borderRouter"],"lan":["wifi"],"wifi":["n"],"bluetooth":["5.0"]},"control":["homeKit","siri"],"homeKitHubType":"hub","powerSource":["wall"],"purchaseLink":"https://www.apple.com/shop/buy-homepod/homepod-mini","expandable":false,"productId":"e5feff15-c052-4697-b4e4-86fdff437315"},"019e1e56-cd76-4782-91aa-5da0696b2428":{"brand":"Enbrighten","model":"Smart Motion Switch","generation":1,"revision":"N/A","category":["switch","sensor"],"type":"switch","subtype":"lightSwitch","senses":["motion"],"network":{"zWave":["plus"]},"powerSource":["wall"],"amazonDP":{"com":"B07226MG2T"},"productId":"019e1e56-cd76-4782-91aa-5da0696b2428"},"3c5367c4-7554-4a5b-8413-22a1f7086720":{"brand":"GIRA + Senic","model":"Friends of Hue Switch","generation":1,"revision":"N/A","category":"switch","type":"switch","subtype":"lightSwitch","network":{"zigbee":[]},"certs":["friendsOfHue"],"powerSource":["self"],"amazonDP":"B07VRDKD8S","productId":"3c5367c4-7554-4a5b-8413-22a1f7086720"},"16bb59bf-43f3-49e6-ab1c-462c5171a78c":{"brand":"Google","model":"Nest Mini","generation":2,"revision":"N/A","category":"hub","type":"proprietary","network":{"lan":["wifi"],"wifi":["2.4GHz","5GHz","AC"],"bluetooth":["5.0"]},"control":["googleAssistant"],"powerSource":["wall"],"purchaseLink":"https://store.google.com/product/google_nest_mini","expandable":false,"productId":"16bb59bf-43f3-49e6-ab1c-462c5171a78c"},"eb4d5fde-9a13-4c0d-b615-cb6598a25749":{"brand":"Google","model":"Nest Hub","generation":2,"revision":"N/A","category":"hub","type":"proprietary","network":{"lan":["wifi"],"wifi":["2.4GHz","5GHz","AC"],"bluetooth":["5.0"],"thread":["borderRouter","matter"]},"control":["googleAssistant"],"powerSource":["wall"],"purchaseLink":"https://store.google.com/product/nest_hub_2nd_gen","expandable":false,"productId":"eb4d5fde-9a13-4c0d-b615-cb6598a25749"},"18967f87-1c04-4494-adb5-8f99b2899217":{"brand":"Ikea","model":"Dirigera","generation":"N/A","revision":"2022","category":"hub","type":"open","network":{"zigbee":["gen3"],"thread":["borderRouter","matter"],"lan":["ethernet"],"ethernet":[]},"control":["brandApp","alexa","googleAssistant","homeKit"],"homeKitHubType":"bridge","powerSource":["wall"],"purchaseLink":"https://www.ikea.com/de/de/p/dirigera-hub-fuer-smarte-produkte-weiss-smart-10503406/","expandable":false,"productId":"18967f87-1c04-4494-adb5-8f99b2899217"},"3f57663c-39f0-452e-ab4c-c749ff4b017d":{"brand":"Ikea","model":"Trådfri","generation":"N/A","revision":"N/A","category":"light","type":"bulb","network":{"zigbee":["gen3"]},"control":[],"powerSource":["wall"],"amazonDP":{"de":"B08NF5ZWSC"},"purchaseLik":"https://www.ikea.com/de/de/p/tradfri-led-leuchtmittel-e27-806-lm-kabellos-dimmbar-farb-und-weissspektrum-rund-opalweiss-70439158/","lumen":806,"varLumen":true,"varKelvin":true,"multicolor":true,"socket":"e27","productId":"3f57663c-39f0-452e-ab4c-c749ff4b017d"},"8fdebdcd-e271-4ffd-9b22-2c3936073ccb":{"brand":"Ikea","model":"Styrbar","generation":"N/A","revision":"2020","category":"switch","type":"switch","subtype":"lightSwitch","network":{"zigbee":[]},"powerSource":["battery"],"purchaseLink":"https://www.ikea.com/de/de/p/styrbar-fernbedienung-smart-weiss-30488363/","productId":"8fdebdcd-e271-4ffd-9b22-2c3936073ccb"},"d48dc897-ee6c-4576-ab0c-518cb4e15e46":{"brand":"Ikea","model":"Trådfri","generation":"N/A","revision":"2020","category":"sensor","senses":["motion"],"network":{"zigbee":[]},"control":[],"powerSource":["battery"],"purchaseLink":"https://www.ikea.com/de/de/p/tradfri-funk-bewegungsmelder-smart-weiss-70429913/","productId":"d48dc897-ee6c-4576-ab0c-518cb4e15e46"},"7538a6f4-6637-4e2a-a2d5-5466f5dde7b4":{"brand":"Ledvance","model":"SMART+ WiFi Candle Multicolour","generation":"N/A","revision":"2022","category":"light","type":"bulb","network":{"lan":["wifi"],"wifi":[]},"control":["brandApp","alexa","googleAssistant"],"powerSource":["wall"],"amazonDP":{"eu":"B08KYBM1VX"},"lumen":470,"varLumen":true,"varKelvin":true,"multicolor":true,"socket":"e14","productId":"7538a6f4-6637-4e2a-a2d5-5466f5dde7b4"},"5a3a2d3c-e498-482d-bc10-91904b583444":{"brand":"Ledvance","model":"SMART+ Candle Tunable White","generation":"N/A","revision":"2022","category":"light","type":"bulb","network":{"bluetooth":[]},"control":["brandApp","alexa","googleAssistant","homeKit"],"powerSource":["wall"],"amazonDP":{"eu":"B08KYBKRPB"},"lumen":470,"varLumen":true,"varKelvin":true,"multicolor":false,"socket":"e14","productId":"5a3a2d3c-e498-482d-bc10-91904b583444"},"d583fb1d-cb98-4008-8af0-21813d0d3651":{"brand":"Ledvance","model":"SMART+ Candle Dimmable","generation":"N/A","revision":"2022","category":"light","type":"bulb","network":{"zigbee":["gen3"]},"powerSource":["wall"],"amazonDP":{"eu":"B07MSPL4LY"},"lumen":470,"varLumen":true,"varKelvin":false,"multicolor":false,"socket":"e14","productId":"d583fb1d-cb98-4008-8af0-21813d0d3651"},"9b560b24-315a-48f9-b504-1410cd374581":{"brand":"Ledvance","model":"Smart+ Motion Sensor","generation":"N/A","revision":"2022","category":"sensor","senses":["motion"],"network":{"lan":["wifi"],"wifi":["2.4GHz"]},"control":["brandApp","alexa"],"powerSource":["wall"],"amazonDP":{"eu":"B09Z6WDGSG"},"productId":"9b560b24-315a-48f9-b504-1410cd374581"},"03137251-6156-45f9-b32e-fc6482cbba32":{"brand":"LIFX","model":"Colour A60 E27","generation":"N/A","revision":"2020","category":"light","type":"bulb","network":{"lan":["wifi"],"wifi":["2.4GHz"]},"control":["brandApp","alexa","googleAssistant","homeKit"],"powerSource":["wall"],"amazonDP":"B08BY2JVJK","lumen":1200,"varLumen":true,"varKelvin":true,"multicolor":true,"socket":"e27","productId":"03137251-6156-45f9-b32e-fc6482cbba32"},"f9455816-348d-4936-97fc-cbf6085ae45e":{"brand":"LIFX","model":"Candle White to Warm E14","generation":"N/A","revision":"2020","category":"light","type":"bulb","network":{"lan":["wifi"],"wifi":["2.4GHz"]},"control":["brandApp","alexa","googleAssistant","homeKit"],"powerSource":["wall"],"amazonDP":"B08BX1FYDZ","lumen":480,"varLumen":true,"varKelvin":true,"multicolor":false,"socket":"e14","productId":"f9455816-348d-4936-97fc-cbf6085ae45e"},"f07f147d-ab84-4f59-848b-44f5142b8f33":{"brand":"OSRAM","model":"Smart+ Motion Sensor","generation":"N/A","revision":"N/A","category":"sensor","senses":["motion","temperature"],"network":{"zigbee":[]},"control":["alexa"],"powerSource":["battery"],"amazonDP":{"eu":"B074KHZZ6B"},"productId":"f07f147d-ab84-4f59-848b-44f5142b8f33"},"30f60724-3466-4198-a6c7-19b97a0ebceb":{"brand":"Philips Hue","model":"Motion Sensor","generation":"N/A","revision":"2021","category":"sensor","senses":["motion"],"network":{"zigbee":["gen3"]},"control":[],"powerSource":["battery"],"amazonDP":{"eu":"B09CV78GV1","com":"B076MGK22M"},"productId":"30f60724-3466-4198-a6c7-19b97a0ebceb"},"5d3b8d85-d615-4858-8814-c4936e968c51":{"brand":"Philips Hue","model":"Smart Button","generation":"N/A","revision":"2021","category":"switch","type":"button","subtype":"lightSwitch","network":{"zigbee":["gen3"]},"powerSource":["battery"],"amazonDP":{"eu":"B09C3MJR24","com":"B07XV1HRVZ"},"productId":"5d3b8d85-d615-4858-8814-c4936e968c51"},"6f205e26-8532-4cbb-90d8-18ca106ca65b":{"brand":"Philips Hue","model":"Tap Dial Switch","generation":"N/A","revision":"2022","category":"switch","type":"dial","subtype":"lightSwitch","network":{"zigbee":["gen3"]},"powerSource":["battery"],"amazonDP":{"eu":"B0B2PQLWD9","com":"B0B6LLKHTM"},"productId":"6f205e26-8532-4cbb-90d8-18ca106ca65b"},"75e6f686-f057-4d84-86a5-95635f43a8be":{"brand":"Philips Hue","model":"Bridge","generation":2,"revision":"2","category":"hub","type":"proprietary","network":{"zigbee":["gen3"],"lan":["ethernet"],"ethernet":[]},"control":["brandApp","alexa","googleAssistant","homeKit","cortana"],"homeKitHubType":"bridge","powerSource":["wall"],"amazonDP":{"eu":"B09CV9F3KR","com":"B016H0QZ7I"},"expandable":false,"productId":"75e6f686-f057-4d84-86a5-95635f43a8be"},"93f468b1-23c4-48e8-87c4-b7c2e13e9828":{"brand":"Philips Hue","model":"Outdoor Sensor","generation":"N/A","revision":"2021","category":"sensor","senses":["motion"],"network":{"zigbee":["gen3"]},"control":[],"powerSource":["battery"],"amazonDP":{"eu":"B09CV7MT5S","com":"B07NDFQF2T"},"productId":"93f468b1-23c4-48e8-87c4-b7c2e13e9828"},"9e1126c1-d336-4f5a-bd44-22718f916d5f":{"brand":"Philips Hue","model":"Wireless Dimmer Switch","generation":2,"revision":"N/A","category":"switch","type":"switch","subtype":"lightSwitch","network":{"zigbee":["gen3"],"bluetooth":[]},"powerSource":["battery"],"amazonDP":{"eu":"B08PKMT2DV"},"purchaseLink":"https://www.philips-hue.com/de-de/p/hue-hue-dimmschalter--neuestes-modell-/8719514274617","productId":"9e1126c1-d336-4f5a-bd44-22718f916d5f"},"e0626e96-0b93-44df-841c-7200a25a82fc":{"brand":"Philips Hue","model":"White and Color Ambience","generation":"N/A","revision":"2022","category":"light","type":"bulb","network":{"zigbee":["gen3"],"bluetooth":[]},"control":["brandApp"],"powerSource":["wall"],"amazonDP":"B099P3CP1K","lumen":1100,"varLumen":true,"varKelvin":true,"multicolor":true,"socket":"e27","productId":"e0626e96-0b93-44df-841c-7200a25a82fc"}}}
