{"count":12,"data":{"2d863444-87aa-46d4-a9c1-0aaafbab1c90":{"brand":"Aeotec","model":"Smart Home Hub","generation":3,"revision":"N/A","category":"hub","type":"open","network":{"zigbee":["gen3"],"zWave":["plus"],"wifi":["2.4GHz","5GHz","AC"]},"control":["alexa","googleAssistant","smartThings"],"powerSource":["wall"],"amazonDP":{"eu":"B08NDH9NXN","com":"B08TWDNQ5Q"},"expandable":false,"productId":"2d863444-87aa-46d4-a9c1-0aaafbab1c90"},"9ee4cade-fccd-4d2a-bc23-6e41d1eb21b9":{"brand":"Aeotec","model":"MultiSensor 6","generation":6,"revision":"N/A","category":"sensor","senses":["humidity","light","motion","uv","temperature","vibration"],"network":{"zWave":["plus","gen5"]},"control":["smartThings"],"powerSource":["wall","battery"],"amazonDP":{"eu":"B0141FQDJQ","com":"B0151Z8ZQY"},"productId":"9ee4cade-fccd-4d2a-bc23-6e41d1eb21b9"},"c846940e-f68c-4b14-808b-5c35dee691de":{"brand":"Aeotec","model":"MultiSensor 7","generation":7,"revision":"N/A","category":"sensor","senses":["humidity","light","motion","uv","temperature","vibration"],"network":{"zWave":["plus","S2","gen7"]},"control":["smartThings"],"powerSource":["wall","battery"],"amazonDP":{"com":"B08XHZP7NV"},"productId":"c846940e-f68c-4b14-808b-5c35dee691de"},"239f42e6-0fa0-474f-b3bc-f1587445e35c":{"brand":"Amazon","model":"Echo","generation":4,"revision":"2020","category":"hub","type":"proprietary","network":{"zigbee":["gen3"],"bluetooth":[],"wifi":["2.4GHz","5GHz","AC"]},"control":["alexa"],"powerSource":["wall"],"amazonDP":{"eu":"B085FXHR38","pl":"B085H3DKLT","com":"B07XKF5RM3"},"expandable":false,"productId":"239f42e6-0fa0-474f-b3bc-f1587445e35c"},"d20c39d8-d1f5-4947-8cd3-b14632cb043a":{"brand":"Amazon","model":"Echo Dot with Clock","generation":4,"revision":"2020","category":"hub","type":"proprietary","network":{"bluetooth":[],"wifi":["2.4GHz","5GHz","AC"]},"control":["alexa"],"powerSource":["wall"],"amazonDP":{"eu":"B084J4KZ8J","com":"B07XJ8C8F7"},"expandable":false,"productId":"d20c39d8-d1f5-4947-8cd3-b14632cb043a"},"eb9c18d9-ba0c-4067-9c68-75b89d5d7392":{"brand":"Amazon","model":"Echo Dot","generation":4,"revision":"2020","category":"hub","type":"proprietary","network":{"bluetooth":[],"wifi":["2.4GHz","5GHz","AC"]},"control":["alexa"],"powerSource":["wall"],"amazonDP":{"eu":"B084DWG2VQ","pl":"B085K45C3","com":"B07XJ8C8F5"},"expandable":false,"productId":"eb9c18d9-ba0c-4067-9c68-75b89d5d7392"},"019e1e56-cd76-4782-91aa-5da0696b2428":{"brand":"Enbrighten","model":"Smart Motion Switch","generation":1,"revision":"N/A","category":["switch","sensor"],"type":"lightSwitch","senses":["motion"],"network":{"zWave":["plus"]},"powerSource":["wall"],"amazonDP":{"com":"B07226MG2T"},"productId":"019e1e56-cd76-4782-91aa-5da0696b2428"},"3c5367c4-7554-4a5b-8413-22a1f7086720":{"brand":"GIRA + Senic","model":"Friends of Hue Switch","generation":1,"revision":"N/A","category":"switch","type":"lightSwitch","network":{"zigbee":[]},"certs":["friendsOfHue"],"powerSource":["self"],"amazonDP":"B07VRDKD8S","productId":"3c5367c4-7554-4a5b-8413-22a1f7086720"},"03137251-6156-45f9-b32e-fc6482cbba32":{"brand":"LIFX","model":"Colour A60 E27","generation":"N/A","revision":2020,"category":"light","type":"bulb","network":{"wifi":["2.4GHz"]},"control":["brandApp","alexa","googleAssistant","homeKit"],"powerSource":["wall"],"amazonDP":"B08BY2JVJK","lumen":1200,"varLumen":true,"varKelvin":true,"multicolor":true,"socket":"e27","productId":"03137251-6156-45f9-b32e-fc6482cbba32"},"f9455816-348d-4936-97fc-cbf6085ae45e":{"brand":"LIFX","model":"Candle White to Warm E14","generation":"N/A","revision":2020,"category":"light","type":"bulb","network":{"wifi":["2.4GHz"]},"control":["brandApp","alexa","googleAssistant","homeKit"],"powerSource":["wall"],"amazonDP":"B08BX1FYDZ","lumen":480,"varLumen":true,"varKelvin":true,"multicolor":false,"socket":"e14","productId":"f9455816-348d-4936-97fc-cbf6085ae45e"},"75e6f686-f057-4d84-86a5-95635f43a8be":{"brand":"Philips Hue","model":"Bridge","generation":2,"revision":2,"category":"hub","type":"proprietary","network":{"zigbee":["gen3"],"ethernet":[]},"control":["brandApp","alexa","googleAssistant","homeKit","cortana"],"powerSource":["wall"],"amazonDP":{"eu":"B09CV9F3KR","com":"B016H0QZ7I"},"expandable":false,"productId":"75e6f686-f057-4d84-86a5-95635f43a8be"},"e0626e96-0b93-44df-841c-7200a25a82fc":{"brand":"Philips Hue","model":"White and Color Ambience","generation":"N/A","revision":2022,"category":"light","type":"bulb","network":{"zigbee":["gen3"],"bluetooth":[]},"control":["brandApp"],"powerSource":["wall"],"amazonDP":"B099P3CP1K","lumen":"1100","varLumen":true,"varKelvin":true,"multicolor":true,"socket":"e27","productId":"e0626e96-0b93-44df-841c-7200a25a82fc"}}}
